kantan_agents/__init__.py
kantan_agents/agent.py
kantan_agents/judge.py
kantan_agents/prompt.py
kantan_agents/rubric.py
kantan_agents/tool_registry.py
kantan_agents/tool_rules.py
kantan_agents/tools_info.py
kantan_agents/tracing.py
kantan_agents/utils.py
kantan_agents-0.1.3.dist-info/METADATA
kantan_agents-0.1.3.dist-info/WHEEL
kantan_agents-0.1.3.dist-info/top_level.txt
kantan_agents-0.1.3.dist-info/RECORD
