Metadata-Version: 2.4
Name: kantan-agents
Version: 0.1.3
Summary: kantan-agents is a thin, opinionated wrapper around the OpenAI Agents SDK that makes observability and evaluation “just happen” by default.
Requires-Python: >=3.10
Requires-Dist: kantan-llm>=0.1.7
Requires-Dist: openai-agents>=0.6.4
